{
  "project": {
    "name": "",
    "slug": "csrinaldi/brain",
    "gitHost": "github.com",
    "gitProjectId": "",
    "owner": ""
  },
  "docs": {
    "language": "en"
  },
  "vcs": {
    "provider": "github"
  },
  "governance": {
    "ignoreList": [
      "**/*.golden.json",
      "**/*.test.mjs",
      ".memory/**",
      "AGENTS.md",
      "openspec/changes/**",
      "openspec/specs/**",
      "openspec/changes/archive/**",
      "package-lock.json",
      "pnpm-lock.yaml",
      "yarn.lock"
    ]
  },
  "reviewer": {
    "handle": "",
    "tokenEnv": "BRAIN_REVIEWER_TOKEN"
  },
  "schemaVersion": "0.3.0"
}
